rerank/__init__.py
rerank/tools/__init__.py
rerank/tools/cohere_rerank.py
rerank/tools/language_detection.py
rerank/tools/utils.py
tests/__init__.py
tests/test_hello_world_tool.py
PA_Tool20240920-0.0.1.dist-info/METADATA
PA_Tool20240920-0.0.1.dist-info/WHEEL
PA_Tool20240920-0.0.1.dist-info/entry_points.txt
PA_Tool20240920-0.0.1.dist-info/top_level.txt
PA_Tool20240920-0.0.1.dist-info/RECORD
