Metadata-Version: 2.1
Name: PA_Tool20240920
Version: 0.0.1
Summary: This is my tools package
